quantastica_qps_api-0.9.16-py3.11-nspkg.pth
quantastica/qps_api/__init__.py
quantastica/qps_api/qps_api.py
quantastica_qps_api-0.9.16.dist-info/licenses/LICENSE
quantastica_qps_api-0.9.16.dist-info/METADATA
quantastica_qps_api-0.9.16.dist-info/WHEEL
quantastica_qps_api-0.9.16.dist-info/namespace_packages.txt
quantastica_qps_api-0.9.16.dist-info/top_level.txt
quantastica_qps_api-0.9.16.dist-info/RECORD
