Metadata-Version: 2.4
Name: quantastica-qps-api
Version: 0.9.16
Summary: Quantastica Quantum Programming Studio API
Home-page: https://github.com/quantastica/qps-api
Author: Quantastica
Author-email: support@quantastica.com
License: Apache License 2.0
Classifier: Development Status :: 4 - Beta
Classifier: License :: OSI Approved :: Apache Software License
Classifier: Programming Language :: Python :: 3
Classifier: Intended Audience :: Science/Research
License-File: LICENSE
Requires-Dist: requests
Dynamic: author
Dynamic: author-email
Dynamic: classifier
Dynamic: description
Dynamic: description-content-type
Dynamic: home-page
Dynamic: license
Dynamic: license-file
Dynamic: requires-dist
Dynamic: summary
